asyncio_telnet/__init__.py
asyncio_telnet/asyncio_telnet.py
asyncio_telnet-0.1.21.dist-info/LICENSE
asyncio_telnet-0.1.21.dist-info/METADATA
asyncio_telnet-0.1.21.dist-info/WHEEL
asyncio_telnet-0.1.21.dist-info/top_level.txt
asyncio_telnet-0.1.21.dist-info/RECORD
