Metadata-Version: 2.1
Name: asyncio-telnet
Version: 0.1.21
Summary: Asyncio-based Telnet library
Home-page: https://github.com/ForceFledgling/asyncio-telnet
Author: Vladimir Penzin
Author-email: pvenv@icloud.com
Keywords: telnet tty asyncio synchronous asyncronous vty vtysh fast simple
Platform: any
Classifier: Development Status :: 5 - Production/Stable
Classifier: Intended Audience :: Developers
Classifier: License :: OSI Approved :: Apache Software License
Classifier: Framework :: AsyncIO
Classifier: Programming Language :: Python :: 3.6
Classifier: Programming Language :: Python :: 3.7
Classifier: Programming Language :: Python :: 3.8
Classifier: Programming Language :: Python :: 3.9
Classifier: Programming Language :: Python :: 3.10
Classifier: Programming Language :: Python :: 3.11
Classifier: Programming Language :: Python :: 3.12
Classifier: Programming Language :: Python :: Implementation :: CPython
Classifier: Operating System :: MacOS
Classifier: Operating System :: POSIX :: Linux
Classifier: Operating System :: Microsoft
Classifier: Topic :: Internet
Classifier: Topic :: Utilities
Classifier: Topic :: Terminals :: Telnet
Classifier: Topic :: Software Development :: Libraries :: Python Modules
Requires-Python: >=3.6
License-File: LICENSE
Requires-Dist: asyncio
